anywidget_glsl/__init__.py
anywidget_glsl/connectors.py
anywidget_glsl/pipeline.py
anywidget_glsl/uniform.py
anywidget_glsl/widget.py
anywidget_glsl/demos/__init__.py
anywidget_glsl/demos/maze.py
anywidget_glsl/filters/__init__.py
anywidget_glsl/filters/blur.py
anywidget_glsl/filters/trail.py
anywidget_glsl/src/glsl.js
anywidget_glsl-1.0.0.data/data/share/anywidget_glsl/src/glsl.js
anywidget_glsl-1.0.0.dist-info/METADATA
anywidget_glsl-1.0.0.dist-info/WHEEL
anywidget_glsl-1.0.0.dist-info/licenses/LICENSE
anywidget_glsl-1.0.0.dist-info/RECORD
