Metadata-Version: 2.4
Name: anywidget-glsl
Version: 1.0.0
Summary: Write GPU-accelerated GLSL shaders in Jupyter notebooks with a Shadertoy-like API
Project-URL: Homepage, https://github.com/manzt/anywidget-glsl
Project-URL: Repository, https://github.com/manzt/anywidget-glsl
Project-URL: Issues, https://github.com/manzt/anywidget-glsl/issues
Project-URL: Documentation, https://github.com/manzt/anywidget-glsl#readme
Author: anywidget-glsl contributors
License: Apache-2.0
License-File: LICENSE
Keywords: anywidget,glsl,gpu,jupyter,notebook,shader,visualization,webgl,widget
Classifier: Development Status :: 5 - Production/Stable
Classifier: Framework :: Jupyter
Classifier: Intended Audience :: Developers
Classifier: Intended Audience :: Science/Research
Classifier: License :: OSI Approved :: Apache Software License
Classifier: Operating System :: OS Independent
Classifier: Programming Language :: Python
Classifier: Programming Language :: Python :: 3
Classifier: Programming Language :: Python :: 3.13
Classifier: Topic :: Multimedia :: Graphics
Classifier: Topic :: Scientific/Engineering :: Visualization
Requires-Python: >=3.13
Requires-Dist: anywidget>=0.9.0
Requires-Dist: marimo>=0.17.2
Requires-Dist: numpy>=2.3.4
Requires-Dist: scgraph-data>=2.0.0
Provides-Extra: dev
Requires-Dist: pytest-cov>=4.1.0; extra == 'dev'
Requires-Dist: pytest>=8.0.0; extra == 'dev'
Requires-Dist: ruff>=0.8.0; extra == 'dev'
